bms/__init__.py
bms/blocks.py
bms/bms.py
bms/core.py
bms/inputs.py
bms/interface.py
bms/blocks/__init__.py
bms/blocks/continuous.py
bms/blocks/nonlinear.py
bms/inputs/__init__.py
bms/inputs/functions.py
bms/inputs/wltp.py
bms/signals/__init__.py
bms/signals/functions.py
bms/signals/wltp.py
bms-0.1.1.dist-info/DESCRIPTION.rst
bms-0.1.1.dist-info/METADATA
bms-0.1.1.dist-info/RECORD
bms-0.1.1.dist-info/WHEEL
bms-0.1.1.dist-info/metadata.json
bms-0.1.1.dist-info/top_level.txt
