Metadata-Version: 2.0
Name: bms
Version: 0.1.1
Summary: Block-Model Simulator for python
Home-page: http://github.com/masfaraud/BMSpy/wiki/
Author: Steven Masfaraud
Author-email: steven@masfaraud.fr
License: Creative Commons Attribution-Share Alike license
Keywords: block model simulation simulator time
Platform: UNKNOWN
Classifier: Topic :: Scientific/Engineering
Classifier: Development Status :: 3 - Alpha
Requires-Dist: dill
Requires-Dist: matplotlib (>=2.0)
Requires-Dist: networkx
Requires-Dist: numpy
